setup.py
examples/__init__.py
examples/invitation_project/__init__.py
examples/invitation_project/manage.py
examples/invitation_project/settings.py
examples/invitation_project/urls.py
invitation/__init__.py
invitation/admin.py
invitation/forms.py
invitation/models.py
invitation/tests.py
invitation/urls.py
invitation/views.py
invitation/management/__init__.py
invitation/management/commands/__init__.py
invitation/management/commands/cleanupinvitation.py
tivix_django_invitation_simplified.egg-info/PKG-INFO
tivix_django_invitation_simplified.egg-info/SOURCES.txt
tivix_django_invitation_simplified.egg-info/dependency_links.txt
tivix_django_invitation_simplified.egg-info/not-zip-safe
tivix_django_invitation_simplified.egg-info/top_level.txt