Metadata-Version: 1.1
Name: tivix-django-invitation-simplified
Version: 0.0.1
Summary: Simple Django app to allow user registration by invitation.
Home-page: https://github.com/Tivix/django-invitation-simplified
Author: Sumit Chachra
Author-email: sumit@tivix.com
License: UNKNOWN
Platform: UNKNOWN
Classifier: Development Status :: 4 - Beta
Classifier: Environment :: Web Environment
Classifier: Intended Audience :: Developers
Classifier: License :: OSI Approved :: BSD License
Classifier: Operating System :: OS Independent
Classifier: Programming Language :: Python
Classifier: Framework :: Django
